data_files_tools/__init__.py
data_files_tools/after_2f_check_process.py
data_files_tools/create_2f_check_prompt.py
data_files_tools/excel_file_2_dmp.py
data_files_tools/json_files_2_csv.py
data_files_tools/merge_files_2_markdown.py
data_files_tools/wait_until_file_nonexists.py
data_files_tools-0.0.4.dist-info/licenses/LICENSE
data_files_tools-0.0.4.dist-info/METADATA
data_files_tools-0.0.4.dist-info/WHEEL
data_files_tools-0.0.4.dist-info/entry_points.txt
data_files_tools-0.0.4.dist-info/top_level.txt
data_files_tools-0.0.4.dist-info/RECORD
