Metadata-Version: 2.4
Name: data_files_tools
Version: 0.0.4
Summary: LLM redis中介的客户端程序
Author-email: Fang JiaWei <fjw12998@hotmail.com>
License-Expression: GPL-3.0-or-later
Project-URL: Homepage, https://gitee.com/sky_flash/data_files_tools
Project-URL: Documentation, https://gitee.com/sky_flash/data_files_tools/docs
Classifier: Programming Language :: Python :: 3
Classifier: Programming Language :: Python :: 3.9
Classifier: Programming Language :: Python :: 3.10
Classifier: Programming Language :: Python :: 3.11
Classifier: Programming Language :: Python :: 3.12
Classifier: Operating System :: OS Independent
Requires-Python: >=3.9
License-File: LICENSE
Requires-Dist: openpyxl<4.0.0,>=3.1.5
Requires-Dist: pandas<3.0.0,>=2.3.3
Dynamic: license-file
